channels_redis_contrib/__init__.py
channels_redis_contrib/core.py
channels_redis_contrib/pubsub.py
channels_redis_contrib/utils.py
channels_redis_contrib-3.4.1.dist-info/LICENSE
channels_redis_contrib-3.4.1.dist-info/METADATA
channels_redis_contrib-3.4.1.dist-info/WHEEL
channels_redis_contrib-3.4.1.dist-info/top_level.txt
channels_redis_contrib-3.4.1.dist-info/RECORD
