Metadata-Version: 2.1
Name: channels-redis-contrib
Version: 3.4.1
Summary: Provides Django Channels channel layers that use Redis as a backing store.
Author-email: Isaac Robert <isaacrobertoluwaseun@gmail.com>
Project-URL: Homepage, https://github.com/isaacrobert33/channels-redis-contrib
Project-URL: Bug Tracker, https://github.com/isaacrobert33/channels-redis-contrib/issues
Classifier: Programming Language :: Python :: 3
Classifier: License :: OSI Approved :: MIT License
Classifier: Operating System :: OS Independent
Requires-Python: >=3.4
License-File: LICENSE
